README.md
setup.cfg
setup.py
binaryio/__init__.py
binaryio/binaryreader.py
binaryio/binarywriter.py
binaryio/open.py
binaryio/seektask.py
binaryio/structs.py
binaryio.egg-info/PKG-INFO
binaryio.egg-info/SOURCES.txt
binaryio.egg-info/dependency_links.txt
binaryio.egg-info/top_level.txt