Metadata-Version: 1.2
Name: binaryio
Version: 1.0.0
Summary: Python package providing binary reading and writing functionality.
Home-page: https://github.com/Syroot/binaryio
Author: Syroot
Author-email: dev@syroot.com
Maintainer: Rajiv Patel
Maintainer-email: rajivpatel36@gmail.com
License: MIT
Download-URL: https://github.com/Syroot/binaryio/archive/1.0.0.tar.gz
Keywords: binarydata io
Platform: UNKNOWN
Requires-Python: >=3
